my_module/__init__.py
my_module/example.py
my_binary_package-0.1.dist-info/METADATA
my_binary_package-0.1.dist-info/WHEEL
my_binary_package-0.1.dist-info/top_level.txt
my_binary_package-0.1.dist-info/RECORD
