Metadata-Version: 2.1
Name: my_binary_package
Version: 0.1
Summary: A simple example package with binary distributions
Home-page: https://github.com/yourusername/my_binary_package
Author: Your Name
Author-email: your.email@example.com
Classifier: Programming Language :: Python :: 3
Classifier: License :: OSI Approved :: MIT License
Classifier: Operating System :: OS Independent
Requires-Python: >=3.6
